[{"t":"2026-07-20T00:36:16.002Z","r":[{"n":"skinopro.com","up":true,"ms":915},{"n":"ainaghventures.com","up":true,"ms":1889},{"n":"aaandsghana.com","up":true,"ms":2031},{"n":"amzendock.com","up":true,"ms":2019},{"n":"airliv8hernetwork.com","up":true,"ms":1419},{"n":"effectivelifeministry.org","up":true,"ms":2749},{"n":"gmwghana.com","up":true,"ms":3035},{"n":"opportunitytoexcel.com","up":true,"ms":4058},{"n":"nestechnology.com","up":false,"ms":1408},{"n":"amorefoundation.org.uk","up":true,"ms":6859},{"n":"uhuruforall.com","up":true,"ms":5867},{"n":"jassmattazz.com","up":true,"ms":3739},{"n":"lansor.co.uk","up":true,"ms":11254}]},{"t":"2026-07-20T04:13:14.265Z","r":[{"n":"skinopro.com","up":true,"ms":146},{"n":"ainaghventures.com","up":true,"ms":368},{"n":"aaandsghana.com","up":true,"ms":1586},{"n":"amzendock.com","up":true,"ms":1996},{"n":"airliv8hernetwork.com","up":true,"ms":865},{"n":"effectivelifeministry.org","up":true,"ms":5244},{"n":"gmwghana.com","up":true,"ms":2316},{"n":"opportunitytoexcel.com","up":true,"ms":5043},{"n":"nestechnology.com","up":false,"ms":1865},{"n":"amorefoundation.org.uk","up":true,"ms":2679},{"n":"uhuruforall.com","up":false,"ms":60001},{"n":"jassmattazz.com","up":true,"ms":8295},{"n":"lansor.co.uk","up":false,"ms":60000}]},{"t":"2026-07-20T07:29:59.292Z","r":[{"n":"skinopro.com","up":true,"ms":373},{"n":"ainaghventures.com","up":true,"ms":2128},{"n":"aaandsghana.com","up":true,"ms":1721},{"n":"amzendock.com","up":true,"ms":568},{"n":"airliv8hernetwork.com","up":true,"ms":809},{"n":"effectivelifeministry.org","up":true,"ms":5196},{"n":"gmwghana.com","up":true,"ms":1889},{"n":"opportunitytoexcel.com","up":true,"ms":5086},{"n":"nestechnology.com","up":false,"ms":188},{"n":"amorefoundation.org.uk","up":true,"ms":2822},{"n":"uhuruforall.com","up":true,"ms":3023},{"n":"jassmattazz.com","up":true,"ms":9132},{"n":"lansor.co.uk","up":true,"ms":7167}]},{"t":"2026-07-20T10:28:37.569Z","r":[{"n":"skinopro.com","up":true,"ms":379},{"n":"ainaghventures.com","up":true,"ms":573},{"n":"aaandsghana.com","up":true,"ms":845},{"n":"amzendock.com","up":true,"ms":775},{"n":"airliv8hernetwork.com","up":true,"ms":1039},{"n":"effectivelifeministry.org","up":false,"ms":60002},{"n":"gmwghana.com","up":true,"ms":1884},{"n":"opportunitytoexcel.com","up":true,"ms":1275},{"n":"nestechnology.com","up":false,"ms":241},{"n":"amorefoundation.org.uk","up":true,"ms":2904},{"n":"uhuruforall.com","up":false,"ms":60001},{"n":"jassmattazz.com","up":true,"ms":3557},{"n":"lansor.co.uk","up":false,"ms":60001}]},{"t":"2026-07-20T12:29:53.713Z","r":[{"n":"skinopro.com","up":true,"ms":314},{"n":"ainaghventures.com","up":true,"ms":435},{"n":"aaandsghana.com","up":true,"ms":723},{"n":"amzendock.com","up":true,"ms":1223},{"n":"airliv8hernetwork.com","up":true,"ms":991},{"n":"effectivelifeministry.org","up":true,"ms":29026},{"n":"gmwghana.com","up":true,"ms":1839},{"n":"opportunitytoexcel.com","up":true,"ms":1825},{"n":"nestechnology.com","up":false,"ms":829},{"n":"amorefoundation.org.uk","up":true,"ms":9802},{"n":"uhuruforall.com","up":true,"ms":59562},{"n":"jassmattazz.com","up":true,"ms":3941},{"n":"lansor.co.uk","up":true,"ms":51277}]},{"t":"2026-07-20T14:38:03.765Z","r":[{"n":"skinopro.com","up":true,"ms":343},{"n":"ainaghventures.com","up":true,"ms":518},{"n":"aaandsghana.com","up":true,"ms":1764},{"n":"amzendock.com","up":true,"ms":812},{"n":"airliv8hernetwork.com","up":true,"ms":957},{"n":"effectivelifeministry.org","up":true,"ms":2632},{"n":"gmwghana.com","up":true,"ms":1874},{"n":"opportunitytoexcel.com","up":true,"ms":1569},{"n":"nestechnology.com","up":false,"ms":828},{"n":"amorefoundation.org.uk","up":true,"ms":2573},{"n":"uhuruforall.com","up":true,"ms":2077},{"n":"jassmattazz.com","up":true,"ms":3709},{"n":"lansor.co.uk","up":true,"ms":3784}]},{"t":"2026-07-20T16:14:39.635Z","r":[{"n":"skinopro.com","up":true,"ms":225},{"n":"ainaghventures.com","up":true,"ms":300},{"n":"aaandsghana.com","up":true,"ms":406},{"n":"amzendock.com","up":true,"ms":1636},{"n":"airliv8hernetwork.com","up":true,"ms":1294},{"n":"effectivelifeministry.org","up":false,"ms":60001},{"n":"gmwghana.com","up":true,"ms":2573},{"n":"opportunitytoexcel.com","up":true,"ms":1030},{"n":"nestechnology.com","up":false,"ms":503},{"n":"amorefoundation.org.uk","up":true,"ms":2427},{"n":"uhuruforall.com","up":true,"ms":5639},{"n":"jassmattazz.com","up":true,"ms":8955},{"n":"lansor.co.uk","up":true,"ms":53782}]},{"t":"2026-07-20T18:20:33.235Z","r":[{"n":"skinopro.com","up":true,"ms":172},{"n":"ainaghventures.com","up":true,"ms":1625},{"n":"aaandsghana.com","up":true,"ms":2169},{"n":"amzendock.com","up":true,"ms":537},{"n":"airliv8hernetwork.com","up":false,"ms":10494},{"n":"effectivelifeministry.org","up":true,"ms":6857},{"n":"gmwghana.com","up":true,"ms":2181},{"n":"opportunitytoexcel.com","up":true,"ms":1327},{"n":"nestechnology.com","up":false,"ms":550},{"n":"amorefoundation.org.uk","up":true,"ms":2143},{"n":"uhuruforall.com","up":true,"ms":1668},{"n":"jassmattazz.com","up":true,"ms":3100},{"n":"lansor.co.uk","up":true,"ms":2893}]},{"t":"2026-07-20T20:01:30.576Z","r":[{"n":"skinopro.com","up":true,"ms":571},{"n":"ainaghventures.com","up":true,"ms":667},{"n":"aaandsghana.com","up":true,"ms":1898},{"n":"amzendock.com","up":true,"ms":1976},{"n":"airliv8hernetwork.com","up":true,"ms":566},{"n":"effectivelifeministry.org","up":true,"ms":2928},{"n":"gmwghana.com","up":true,"ms":6940},{"n":"opportunitytoexcel.com","up":true,"ms":1529},{"n":"nestechnology.com","up":false,"ms":998},{"n":"amorefoundation.org.uk","up":true,"ms":4049},{"n":"uhuruforall.com","up":true,"ms":2789},{"n":"jassmattazz.com","up":true,"ms":5384},{"n":"lansor.co.uk","up":true,"ms":38164}]},{"t":"2026-07-20T21:12:40.202Z","r":[{"n":"skinopro.com","up":true,"ms":262},{"n":"ainaghventures.com","up":true,"ms":447},{"n":"aaandsghana.com","up":true,"ms":705},{"n":"amzendock.com","up":true,"ms":705},{"n":"airliv8hernetwork.com","up":true,"ms":1048},{"n":"effectivelifeministry.org","up":true,"ms":1923},{"n":"gmwghana.com","up":true,"ms":1725},{"n":"opportunitytoexcel.com","up":true,"ms":1196},{"n":"nestechnology.com","up":false,"ms":735},{"n":"amorefoundation.org.uk","up":true,"ms":3024},{"n":"uhuruforall.com","up":true,"ms":2479},{"n":"jassmattazz.com","up":true,"ms":3220},{"n":"lansor.co.uk","up":true,"ms":11189}]},{"t":"2026-07-20T22:13:52.449Z","r":[{"n":"skinopro.com","up":true,"ms":493},{"n":"ainaghventures.com","up":true,"ms":562},{"n":"aaandsghana.com","up":true,"ms":1877},{"n":"amzendock.com","up":true,"ms":822},{"n":"airliv8hernetwork.com","up":true,"ms":656},{"n":"effectivelifeministry.org","up":true,"ms":5987},{"n":"gmwghana.com","up":true,"ms":2041},{"n":"opportunitytoexcel.com","up":true,"ms":6501},{"n":"nestechnology.com","up":false,"ms":274},{"n":"amorefoundation.org.uk","up":true,"ms":3583},{"n":"uhuruforall.com","up":true,"ms":6549},{"n":"jassmattazz.com","up":true,"ms":3965},{"n":"lansor.co.uk","up":true,"ms":3654}]},{"t":"2026-07-20T23:15:02.540Z","r":[{"n":"skinopro.com","up":true,"ms":294},{"n":"ainaghventures.com","up":true,"ms":392},{"n":"aaandsghana.com","up":true,"ms":708},{"n":"amzendock.com","up":true,"ms":601},{"n":"airliv8hernetwork.com","up":true,"ms":845},{"n":"effectivelifeministry.org","up":true,"ms":2371},{"n":"gmwghana.com","up":true,"ms":1410},{"n":"opportunitytoexcel.com","up":true,"ms":4313},{"n":"nestechnology.com","up":false,"ms":765},{"n":"amorefoundation.org.uk","up":true,"ms":2790},{"n":"uhuruforall.com","up":true,"ms":5240},{"n":"jassmattazz.com","up":true,"ms":3418},{"n":"lansor.co.uk","up":true,"ms":4878}]},{"t":"2026-07-21T00:09:56.977Z","r":[{"n":"skinopro.com","up":true,"ms":456},{"n":"ainaghventures.com","up":true,"ms":592},{"n":"aaandsghana.com","up":true,"ms":2786},{"n":"amzendock.com","up":true,"ms":4143},{"n":"airliv8hernetwork.com","up":true,"ms":630},{"n":"effectivelifeministry.org","up":true,"ms":13583},{"n":"gmwghana.com","up":true,"ms":3287},{"n":"opportunitytoexcel.com","up":true,"ms":1413},{"n":"nestechnology.com","up":false,"ms":322},{"n":"amorefoundation.org.uk","up":true,"ms":2728},{"n":"uhuruforall.com","up":true,"ms":6581},{"n":"jassmattazz.com","up":true,"ms":3735},{"n":"lansor.co.uk","up":true,"ms":9186}]},{"t":"2026-07-21T03:42:22.455Z","r":[{"n":"skinopro.com","up":false,"ms":675},{"n":"ainaghventures.com","up":true,"ms":512},{"n":"aaandsghana.com","up":true,"ms":644},{"n":"amzendock.com","up":true,"ms":775},{"n":"airliv8hernetwork.com","up":true,"ms":977},{"n":"effectivelifeministry.org","up":true,"ms":28717},{"n":"gmwghana.com","up":true,"ms":19797},{"n":"opportunitytoexcel.com","up":true,"ms":1636},{"n":"nestechnology.com","up":false,"ms":742},{"n":"amorefoundation.org.uk","up":true,"ms":2256},{"n":"uhuruforall.com","up":false,"ms":60000},{"n":"jassmattazz.com","up":true,"ms":4864},{"n":"lansor.co.uk","up":true,"ms":45294}]},{"t":"2026-07-21T06:15:26.039Z","r":[{"n":"skinopro.com","up":true,"ms":236},{"n":"ainaghventures.com","up":true,"ms":516},{"n":"aaandsghana.com","up":true,"ms":2942},{"n":"amzendock.com","up":true,"ms":10401},{"n":"airliv8hernetwork.com","up":true,"ms":1039},{"n":"effectivelifeministry.org","up":false,"ms":23},{"n":"gmwghana.com","up":true,"ms":11251},{"n":"opportunitytoexcel.com","up":true,"ms":5404},{"n":"nestechnology.com","up":false,"ms":361},{"n":"amorefoundation.org.uk","up":true,"ms":5976},{"n":"uhuruforall.com","up":false,"ms":22},{"n":"jassmattazz.com","up":false,"ms":21},{"n":"lansor.co.uk","up":false,"ms":21}]},{"t":"2026-07-21T08:48:34.662Z","r":[{"n":"skinopro.com","up":true,"ms":433},{"n":"ainaghventures.com","up":true,"ms":2055},{"n":"aaandsghana.com","up":true,"ms":642},{"n":"amzendock.com","up":true,"ms":96},{"n":"airliv8hernetwork.com","up":true,"ms":731},{"n":"effectivelifeministry.org","up":false,"ms":60000},{"n":"gmwghana.com","up":true,"ms":24103},{"n":"opportunitytoexcel.com","up":true,"ms":3748},{"n":"nestechnology.com","up":false,"ms":532},{"n":"amorefoundation.org.uk","up":true,"ms":2288},{"n":"uhuruforall.com","up":false,"ms":60001},{"n":"jassmattazz.com","up":true,"ms":3256},{"n":"lansor.co.uk","up":false,"ms":60000}]},{"t":"2026-07-21T10:53:29.717Z","r":[{"n":"skinopro.com","up":false,"ms":811},{"n":"ainaghventures.com","up":true,"ms":436},{"n":"aaandsghana.com","up":true,"ms":655},{"n":"amzendock.com","up":true,"ms":66},{"n":"airliv8hernetwork.com","up":true,"ms":936},{"n":"effectivelifeministry.org","up":true,"ms":1644},{"n":"gmwghana.com","up":true,"ms":28761},{"n":"opportunitytoexcel.com","up":true,"ms":1642},{"n":"nestechnology.com","up":false,"ms":364},{"n":"amorefoundation.org.uk","up":true,"ms":9036},{"n":"uhuruforall.com","up":false,"ms":60000},{"n":"jassmattazz.com","up":true,"ms":4785},{"n":"lansor.co.uk","up":true,"ms":15488}]},{"t":"2026-07-21T12:17:56.815Z","r":[{"n":"skinopro.com","up":false,"ms":729},{"n":"ainaghventures.com","up":true,"ms":168},{"n":"aaandsghana.com","up":true,"ms":509},{"n":"amzendock.com","up":true,"ms":442},{"n":"airliv8hernetwork.com","up":true,"ms":1072},{"n":"effectivelifeministry.org","up":false,"ms":26},{"n":"gmwghana.com","up":true,"ms":49747},{"n":"opportunitytoexcel.com","up":true,"ms":1206},{"n":"nestechnology.com","up":false,"ms":783},{"n":"amorefoundation.org.uk","up":true,"ms":4674},{"n":"uhuruforall.com","up":false,"ms":22},{"n":"jassmattazz.com","up":false,"ms":26},{"n":"lansor.co.uk","up":false,"ms":26}]},{"t":"2026-07-21T14:27:59.476Z","r":[{"n":"skinopro.com","up":true,"ms":441},{"n":"ainaghventures.com","up":true,"ms":2222},{"n":"aaandsghana.com","up":true,"ms":1386},{"n":"amzendock.com","up":true,"ms":41192},{"n":"airliv8hernetwork.com","up":true,"ms":779},{"n":"effectivelifeministry.org","up":true,"ms":1770},{"n":"gmwghana.com","up":true,"ms":39794},{"n":"opportunitytoexcel.com","up":true,"ms":4119},{"n":"nestechnology.com","up":false,"ms":628},{"n":"amorefoundation.org.uk","up":true,"ms":3225},{"n":"uhuruforall.com","up":true,"ms":10233},{"n":"jassmattazz.com","up":true,"ms":4374},{"n":"lansor.co.uk","up":true,"ms":6997}]},{"t":"2026-07-21T15:58:56.347Z","r":[{"n":"skinopro.com","up":true,"ms":216},{"n":"ainaghventures.com","up":true,"ms":1762},{"n":"aaandsghana.com","up":true,"ms":989},{"n":"amzendock.com","up":true,"ms":5747},{"n":"airliv8hernetwork.com","up":true,"ms":1356},{"n":"effectivelifeministry.org","up":true,"ms":14969},{"n":"gmwghana.com","up":true,"ms":8404},{"n":"opportunitytoexcel.com","up":true,"ms":1316},{"n":"nestechnology.com","up":false,"ms":448},{"n":"amorefoundation.org.uk","up":true,"ms":2608},{"n":"uhuruforall.com","up":true,"ms":1705},{"n":"jassmattazz.com","up":true,"ms":3777},{"n":"lansor.co.uk","up":true,"ms":4818}]},{"t":"2026-07-21T17:16:16.204Z","r":[{"n":"skinopro.com","up":true,"ms":264},{"n":"ainaghventures.com","up":true,"ms":407},{"n":"aaandsghana.com","up":true,"ms":539},{"n":"amzendock.com","up":true,"ms":25092},{"n":"airliv8hernetwork.com","up":true,"ms":866},{"n":"effectivelifeministry.org","up":true,"ms":56023},{"n":"gmwghana.com","up":true,"ms":27804},{"n":"opportunitytoexcel.com","up":true,"ms":1241},{"n":"nestechnology.com","up":false,"ms":845},{"n":"amorefoundation.org.uk","up":true,"ms":2424},{"n":"uhuruforall.com","up":true,"ms":46327},{"n":"jassmattazz.com","up":true,"ms":3320},{"n":"lansor.co.uk","up":true,"ms":37724}]},{"t":"2026-07-21T18:41:07.340Z","r":[{"n":"skinopro.com","up":true,"ms":278},{"n":"ainaghventures.com","up":true,"ms":445},{"n":"aaandsghana.com","up":true,"ms":497},{"n":"amzendock.com","up":true,"ms":673},{"n":"airliv8hernetwork.com","up":true,"ms":734},{"n":"effectivelifeministry.org","up":true,"ms":10957},{"n":"gmwghana.com","up":true,"ms":28483},{"n":"opportunitytoexcel.com","up":true,"ms":1161},{"n":"nestechnology.com","up":false,"ms":749},{"n":"amorefoundation.org.uk","up":true,"ms":2077},{"n":"uhuruforall.com","up":true,"ms":2823},{"n":"jassmattazz.com","up":true,"ms":3663},{"n":"lansor.co.uk","up":true,"ms":3007}]},{"t":"2026-07-21T20:06:40.461Z","r":[{"n":"skinopro.com","up":true,"ms":193},{"n":"ainaghventures.com","up":true,"ms":220},{"n":"aaandsghana.com","up":true,"ms":440},{"n":"amzendock.com","up":true,"ms":27844},{"n":"airliv8hernetwork.com","up":true,"ms":903},{"n":"effectivelifeministry.org","up":true,"ms":14423},{"n":"gmwghana.com","up":true,"ms":26377},{"n":"opportunitytoexcel.com","up":true,"ms":953},{"n":"nestechnology.com","up":false,"ms":448},{"n":"amorefoundation.org.uk","up":true,"ms":3290},{"n":"uhuruforall.com","up":true,"ms":34742},{"n":"jassmattazz.com","up":true,"ms":3543},{"n":"lansor.co.uk","up":true,"ms":1446}]},{"t":"2026-07-21T21:21:52.788Z","r":[{"n":"skinopro.com","up":true,"ms":432},{"n":"ainaghventures.com","up":true,"ms":1800},{"n":"aaandsghana.com","up":true,"ms":664},{"n":"amzendock.com","up":true,"ms":1071},{"n":"airliv8hernetwork.com","up":true,"ms":660},{"n":"effectivelifeministry.org","up":true,"ms":1200},{"n":"gmwghana.com","up":true,"ms":15613},{"n":"opportunitytoexcel.com","up":true,"ms":1582},{"n":"nestechnology.com","up":false,"ms":799},{"n":"amorefoundation.org.uk","up":true,"ms":2346},{"n":"uhuruforall.com","up":true,"ms":4484},{"n":"jassmattazz.com","up":true,"ms":3371},{"n":"lansor.co.uk","up":true,"ms":4933}]},{"t":"2026-07-21T22:25:40.069Z","r":[{"n":"skinopro.com","up":true,"ms":237},{"n":"ainaghventures.com","up":true,"ms":1487},{"n":"aaandsghana.com","up":true,"ms":523},{"n":"amzendock.com","up":true,"ms":12572},{"n":"airliv8hernetwork.com","up":true,"ms":790},{"n":"effectivelifeministry.org","up":true,"ms":9923},{"n":"gmwghana.com","up":true,"ms":42378},{"n":"opportunitytoexcel.com","up":true,"ms":1076},{"n":"nestechnology.com","up":false,"ms":530},{"n":"amorefoundation.org.uk","up":true,"ms":2102},{"n":"uhuruforall.com","up":true,"ms":3602},{"n":"jassmattazz.com","up":true,"ms":9098},{"n":"lansor.co.uk","up":true,"ms":2744}]},{"t":"2026-07-21T23:25:37.207Z","r":[{"n":"skinopro.com","up":true,"ms":195},{"n":"ainaghventures.com","up":true,"ms":2140},{"n":"aaandsghana.com","up":true,"ms":1847},{"n":"amzendock.com","up":true,"ms":851},{"n":"airliv8hernetwork.com","up":true,"ms":1116},{"n":"effectivelifeministry.org","up":true,"ms":6419},{"n":"gmwghana.com","up":true,"ms":9723},{"n":"opportunitytoexcel.com","up":true,"ms":1387},{"n":"nestechnology.com","up":false,"ms":452},{"n":"amorefoundation.org.uk","up":true,"ms":2189},{"n":"uhuruforall.com","up":true,"ms":18670},{"n":"jassmattazz.com","up":true,"ms":3760},{"n":"lansor.co.uk","up":true,"ms":3433}]},{"t":"2026-07-22T00:13:47.883Z","r":[{"n":"skinopro.com","up":true,"ms":445},{"n":"ainaghventures.com","up":true,"ms":6496},{"n":"aaandsghana.com","up":true,"ms":1760},{"n":"amzendock.com","up":false,"ms":10492},{"n":"airliv8hernetwork.com","up":true,"ms":4975},{"n":"effectivelifeministry.org","up":true,"ms":5304},{"n":"gmwghana.com","up":false,"ms":10494},{"n":"opportunitytoexcel.com","up":true,"ms":8047},{"n":"nestechnology.com","up":false,"ms":260},{"n":"amorefoundation.org.uk","up":true,"ms":6542},{"n":"uhuruforall.com","up":true,"ms":6159},{"n":"jassmattazz.com","up":true,"ms":7850},{"n":"lansor.co.uk","up":true,"ms":6978}]},{"t":"2026-07-22T03:47:35.142Z","r":[{"n":"skinopro.com","up":false,"ms":685},{"n":"ainaghventures.com","up":true,"ms":4661},{"n":"aaandsghana.com","up":true,"ms":513},{"n":"amzendock.com","up":false,"ms":10488},{"n":"airliv8hernetwork.com","up":true,"ms":4954},{"n":"effectivelifeministry.org","up":true,"ms":5420},{"n":"gmwghana.com","up":false,"ms":10488},{"n":"opportunitytoexcel.com","up":true,"ms":8222},{"n":"nestechnology.com","up":false,"ms":368},{"n":"amorefoundation.org.uk","up":true,"ms":17885},{"n":"uhuruforall.com","up":true,"ms":24524},{"n":"jassmattazz.com","up":true,"ms":14908},{"n":"lansor.co.uk","up":true,"ms":46981}]},{"t":"2026-07-22T06:17:30.672Z","r":[{"n":"skinopro.com","up":true,"ms":889},{"n":"ainaghventures.com","up":true,"ms":410},{"n":"aaandsghana.com","up":true,"ms":1139},{"n":"amzendock.com","up":false,"ms":10489},{"n":"airliv8hernetwork.com","up":true,"ms":1017},{"n":"effectivelifeministry.org","up":true,"ms":34796},{"n":"gmwghana.com","up":false,"ms":10488},{"n":"opportunitytoexcel.com","up":true,"ms":3904},{"n":"nestechnology.com","up":false,"ms":186},{"n":"amorefoundation.org.uk","up":true,"ms":3077},{"n":"uhuruforall.com","up":true,"ms":4798},{"n":"jassmattazz.com","up":true,"ms":3439},{"n":"lansor.co.uk","up":true,"ms":31197}]},{"t":"2026-07-22T08:45:50.654Z","r":[{"n":"skinopro.com","up":true,"ms":418},{"n":"ainaghventures.com","up":true,"ms":578},{"n":"aaandsghana.com","up":true,"ms":1565},{"n":"amzendock.com","up":true,"ms":1020},{"n":"airliv8hernetwork.com","up":true,"ms":629},{"n":"effectivelifeministry.org","up":true,"ms":2874},{"n":"gmwghana.com","up":true,"ms":8781},{"n":"opportunitytoexcel.com","up":true,"ms":1619},{"n":"nestechnology.com","up":false,"ms":864},{"n":"amorefoundation.org.uk","up":true,"ms":3278},{"n":"uhuruforall.com","up":true,"ms":1877},{"n":"jassmattazz.com","up":true,"ms":3878},{"n":"lansor.co.uk","up":true,"ms":3376}]},{"t":"2026-07-22T10:54:37.886Z","r":[{"n":"skinopro.com","up":true,"ms":246},{"n":"ainaghventures.com","up":true,"ms":226},{"n":"aaandsghana.com","up":true,"ms":682},{"n":"amzendock.com","up":true,"ms":2334},{"n":"airliv8hernetwork.com","up":true,"ms":938},{"n":"effectivelifeministry.org","up":true,"ms":1120},{"n":"gmwghana.com","up":true,"ms":2144},{"n":"opportunitytoexcel.com","up":true,"ms":1619},{"n":"nestechnology.com","up":false,"ms":180},{"n":"amorefoundation.org.uk","up":true,"ms":3281},{"n":"uhuruforall.com","up":true,"ms":15274},{"n":"jassmattazz.com","up":true,"ms":3954},{"n":"lansor.co.uk","up":true,"ms":43149}]},{"t":"2026-07-22T12:22:27.906Z","r":[{"n":"skinopro.com","up":true,"ms":273},{"n":"ainaghventures.com","up":true,"ms":446},{"n":"aaandsghana.com","up":true,"ms":396},{"n":"amzendock.com","up":true,"ms":4440},{"n":"airliv8hernetwork.com","up":true,"ms":561},{"n":"effectivelifeministry.org","up":false,"ms":27623},{"n":"gmwghana.com","up":true,"ms":3659},{"n":"opportunitytoexcel.com","up":true,"ms":1408},{"n":"nestechnology.com","up":false,"ms":866},{"n":"amorefoundation.org.uk","up":true,"ms":2701},{"n":"uhuruforall.com","up":true,"ms":11957},{"n":"jassmattazz.com","up":true,"ms":3783},{"n":"lansor.co.uk","up":false,"ms":27622}]},{"t":"2026-07-22T14:30:44.983Z","r":[{"n":"skinopro.com","up":true,"ms":459},{"n":"ainaghventures.com","up":true,"ms":9278},{"n":"aaandsghana.com","up":true,"ms":770},{"n":"amzendock.com","up":true,"ms":817},{"n":"airliv8hernetwork.com","up":true,"ms":545},{"n":"effectivelifeministry.org","up":true,"ms":34019},{"n":"gmwghana.com","up":true,"ms":2453},{"n":"opportunitytoexcel.com","up":true,"ms":9070},{"n":"nestechnology.com","up":false,"ms":715},{"n":"amorefoundation.org.uk","up":true,"ms":3354},{"n":"uhuruforall.com","up":true,"ms":58790},{"n":"jassmattazz.com","up":true,"ms":3564},{"n":"lansor.co.uk","up":true,"ms":3196}]},{"t":"2026-07-22T15:58:30.077Z","r":[{"n":"skinopro.com","up":true,"ms":244},{"n":"ainaghventures.com","up":true,"ms":2213},{"n":"aaandsghana.com","up":true,"ms":524},{"n":"amzendock.com","up":true,"ms":652},{"n":"airliv8hernetwork.com","up":true,"ms":984},{"n":"effectivelifeministry.org","up":true,"ms":911},{"n":"gmwghana.com","up":true,"ms":7960},{"n":"opportunitytoexcel.com","up":true,"ms":1313},{"n":"nestechnology.com","up":false,"ms":528},{"n":"amorefoundation.org.uk","up":true,"ms":2440},{"n":"uhuruforall.com","up":true,"ms":3363},{"n":"jassmattazz.com","up":true,"ms":4177},{"n":"lansor.co.uk","up":true,"ms":4493}]},{"t":"2026-07-22T17:15:16.725Z","r":[{"n":"skinopro.com","up":true,"ms":282},{"n":"ainaghventures.com","up":true,"ms":379},{"n":"aaandsghana.com","up":true,"ms":434},{"n":"amzendock.com","up":true,"ms":638},{"n":"airliv8hernetwork.com","up":true,"ms":579},{"n":"effectivelifeministry.org","up":true,"ms":1604},{"n":"gmwghana.com","up":true,"ms":1494},{"n":"opportunitytoexcel.com","up":true,"ms":1033},{"n":"nestechnology.com","up":false,"ms":311},{"n":"amorefoundation.org.uk","up":true,"ms":2532},{"n":"uhuruforall.com","up":true,"ms":1049},{"n":"jassmattazz.com","up":true,"ms":2981},{"n":"lansor.co.uk","up":true,"ms":57022}]},{"t":"2026-07-22T18:38:00.592Z","r":[{"n":"skinopro.com","up":true,"ms":226},{"n":"ainaghventures.com","up":true,"ms":462},{"n":"aaandsghana.com","up":true,"ms":594},{"n":"amzendock.com","up":true,"ms":3634},{"n":"airliv8hernetwork.com","up":true,"ms":924},{"n":"effectivelifeministry.org","up":false,"ms":60000},{"n":"gmwghana.com","up":true,"ms":2958},{"n":"opportunitytoexcel.com","up":true,"ms":1428},{"n":"nestechnology.com","up":false,"ms":898},{"n":"amorefoundation.org.uk","up":true,"ms":2768},{"n":"uhuruforall.com","up":true,"ms":3538},{"n":"jassmattazz.com","up":true,"ms":3094},{"n":"lansor.co.uk","up":true,"ms":3790}]},{"t":"2026-07-22T19:54:46.664Z","r":[{"n":"skinopro.com","up":true,"ms":187},{"n":"ainaghventures.com","up":true,"ms":173},{"n":"aaandsghana.com","up":true,"ms":504},{"n":"amzendock.com","up":false,"ms":12},{"n":"airliv8hernetwork.com","up":true,"ms":849},{"n":"effectivelifeministry.org","up":false,"ms":9},{"n":"gmwghana.com","up":false,"ms":17},{"n":"opportunitytoexcel.com","up":true,"ms":1338},{"n":"nestechnology.com","up":false,"ms":493},{"n":"amorefoundation.org.uk","up":true,"ms":2766},{"n":"uhuruforall.com","up":false,"ms":9},{"n":"jassmattazz.com","up":false,"ms":10},{"n":"lansor.co.uk","up":false,"ms":12}]},{"t":"2026-07-22T20:53:37.462Z","r":[{"n":"skinopro.com","up":true,"ms":392},{"n":"ainaghventures.com","up":true,"ms":558},{"n":"aaandsghana.com","up":true,"ms":697},{"n":"amzendock.com","up":true,"ms":2671},{"n":"airliv8hernetwork.com","up":true,"ms":498},{"n":"effectivelifeministry.org","up":true,"ms":14711},{"n":"gmwghana.com","up":true,"ms":2098},{"n":"opportunitytoexcel.com","up":true,"ms":5708},{"n":"nestechnology.com","up":false,"ms":852},{"n":"amorefoundation.org.uk","up":true,"ms":2804},{"n":"uhuruforall.com","up":true,"ms":20797},{"n":"jassmattazz.com","up":true,"ms":8085},{"n":"lansor.co.uk","up":true,"ms":2387}]}]