{
  "generatedAt": "2026-07-22T19:54:46.664Z",
  "dashboardUrl": "https://reskino.github.io/site-monitor/",
  "results": [
    {
      "name": "skinopro.com",
      "url": "https://skinopro.com",
      "up": true,
      "status": 200,
      "ms": 187,
      "slow": false,
      "error": null,
      "tries": 1,
      "checkedAt": "2026-07-22T19:54:35.899Z"
    },
    {
      "name": "ainaghventures.com",
      "url": "https://ainaghventures.com",
      "up": true,
      "status": 200,
      "ms": 173,
      "slow": false,
      "error": null,
      "tries": 1,
      "checkedAt": "2026-07-22T19:54:35.943Z"
    },
    {
      "name": "aaandsghana.com",
      "url": "https://aaandsghana.com",
      "up": true,
      "status": 200,
      "ms": 504,
      "slow": false,
      "error": null,
      "tries": 1,
      "checkedAt": "2026-07-22T19:54:36.275Z"
    },
    {
      "name": "amzendock.com",
      "url": "https://amzendock.com",
      "up": false,
      "status": 415,
      "ms": 12,
      "slow": false,
      "error": "HTTP 415",
      "tries": 3,
      "checkedAt": "2026-07-22T19:54:44.249Z"
    },
    {
      "name": "airliv8hernetwork.com",
      "url": "https://airliv8hernetwork.com",
      "up": true,
      "status": 200,
      "ms": 849,
      "slow": false,
      "error": null,
      "tries": 1,
      "checkedAt": "2026-07-22T19:54:36.623Z"
    },
    {
      "name": "effectivelifeministry.org",
      "url": "https://effectivelifeministry.org",
      "up": false,
      "status": 415,
      "ms": 9,
      "slow": false,
      "error": "HTTP 415",
      "tries": 3,
      "checkedAt": "2026-07-22T19:54:44.677Z"
    },
    {
      "name": "gmwghana.com",
      "url": "https://gmwghana.com",
      "up": false,
      "status": 415,
      "ms": 17,
      "slow": false,
      "error": "HTTP 415",
      "tries": 3,
      "checkedAt": "2026-07-22T19:54:44.833Z"
    },
    {
      "name": "opportunitytoexcel.com",
      "url": "https://opportunitytoexcel.com",
      "up": true,
      "status": 200,
      "ms": 1338,
      "slow": false,
      "error": null,
      "tries": 1,
      "checkedAt": "2026-07-22T19:54:37.114Z"
    },
    {
      "name": "nestechnology.com",
      "url": "https://nestechnology.com",
      "up": false,
      "status": 0,
      "ms": 493,
      "slow": false,
      "error": "Domain not found (DNS)",
      "tries": 3,
      "checkedAt": "2026-07-22T19:54:46.664Z"
    },
    {
      "name": "amorefoundation.org.uk",
      "url": "https://amorefoundation.org.uk",
      "up": true,
      "status": 200,
      "ms": 2766,
      "slow": false,
      "error": null,
      "tries": 1,
      "checkedAt": "2026-07-22T19:54:38.544Z"
    },
    {
      "name": "uhuruforall.com",
      "url": "https://uhuruforall.com",
      "up": false,
      "status": 415,
      "ms": 9,
      "slow": false,
      "error": "HTTP 415",
      "tries": 3,
      "checkedAt": "2026-07-22T19:54:45.650Z"
    },
    {
      "name": "jassmattazz.com",
      "url": "https://jassmattazz.com",
      "up": false,
      "status": 415,
      "ms": 10,
      "slow": false,
      "error": "HTTP 415",
      "tries": 3,
      "checkedAt": "2026-07-22T19:54:45.361Z"
    },
    {
      "name": "lansor.co.uk",
      "url": "https://lansor.co.uk",
      "up": false,
      "status": 415,
      "ms": 12,
      "slow": false,
      "error": "HTTP 415",
      "tries": 3,
      "checkedAt": "2026-07-22T19:54:45.695Z"
    }
  ]
}